{
 "registry": {
  "event_cement_t30": {
   "fn": "event_drift",
   "sector": "cement",
   "leader": "ULTRACEMCO.NS",
   "threshold": 0.03,
   "hold": 3
  },
  "event_cement_t40": {
   "fn": "event_drift",
   "sector": "cement",
   "leader": "ULTRACEMCO.NS",
   "threshold": 0.04,
   "hold": 3
  },
  "event_cement_t50": {
   "fn": "event_drift",
   "sector": "cement",
   "leader": "ULTRACEMCO.NS",
   "threshold": 0.05,
   "hold": 3
  },
  "event_infra_t30": {
   "fn": "event_drift",
   "sector": "infra",
   "leader": "LT.NS",
   "threshold": 0.03,
   "hold": 3
  },
  "event_infra_t40": {
   "fn": "event_drift",
   "sector": "infra",
   "leader": "LT.NS",
   "threshold": 0.04,
   "hold": 3
  },
  "event_infra_t50": {
   "fn": "event_drift",
   "sector": "infra",
   "leader": "LT.NS",
   "threshold": 0.05,
   "hold": 3
  },
  "event_steel_t30": {
   "fn": "event_drift",
   "sector": "steel",
   "leader": "TATASTEEL.NS",
   "threshold": 0.03,
   "hold": 3
  },
  "event_steel_t40": {
   "fn": "event_drift",
   "sector": "steel",
   "leader": "TATASTEEL.NS",
   "threshold": 0.04,
   "hold": 3
  },
  "event_steel_t50": {
   "fn": "event_drift",
   "sector": "steel",
   "leader": "TATASTEEL.NS",
   "threshold": 0.05,
   "hold": 3
  },
  "mom_cement_lb40": {
   "fn": "momentum",
   "sector": "cement",
   "lookback": 40,
   "top_frac": 0.34
  },
  "mom_cement_lb60": {
   "fn": "momentum",
   "sector": "cement",
   "lookback": 60,
   "top_frac": 0.34
  },
  "mom_cement_lb90": {
   "fn": "momentum",
   "sector": "cement",
   "lookback": 90,
   "top_frac": 0.34
  },
  "mom_infra_lb40": {
   "fn": "momentum",
   "sector": "infra",
   "lookback": 40,
   "top_frac": 0.34
  },
  "mom_infra_lb60": {
   "fn": "momentum",
   "sector": "infra",
   "lookback": 60,
   "top_frac": 0.34
  },
  "mom_infra_lb90": {
   "fn": "momentum",
   "sector": "infra",
   "lookback": 90,
   "top_frac": 0.34
  },
  "mom_pipes_tiles_lb40": {
   "fn": "momentum",
   "sector": "pipes_tiles",
   "lookback": 40,
   "top_frac": 0.34
  },
  "mom_pipes_tiles_lb60": {
   "fn": "momentum",
   "sector": "pipes_tiles",
   "lookback": 60,
   "top_frac": 0.34
  },
  "mom_pipes_tiles_lb90": {
   "fn": "momentum",
   "sector": "pipes_tiles",
   "lookback": 90,
   "top_frac": 0.34
  },
  "input_cost_lag": {
   "fn": "input_cost",
   "sector": "cement",
   "proxy": "TATASTEEL.NS",
   "lb": 20,
   "drop": -0.05
  },
  "monsoon_cement": {
   "fn": "monsoon",
   "csv": "imd_rainfall_departure.csv",
   "lag": 10,
   "sector": "cement",
   "thresh": 10.0
  }
 },
 "contestants": {
  "event_cement_t30": {
   "rung": 0,
   "days_on_rung": 3,
   "equity": 1.0,
   "peak": 1.0,
   "positions": {},
   "trades": 0,
   "days_in_market": 0,
   "sum_ret": 0.0,
   "sum_sq": 0.0,
   "paper_failures": 0,
   "retired": false,
   "history": [
    [
     "2026-07-13",
     0.0,
     1.0
    ],
    [
     "2026-07-10",
     0.0,
     1.0
    ],
    [
     "2026-07-10",
     0.0,
     1.0
    ]
   ]
  },
  "event_cement_t40": {
   "rung": 0,
   "days_on_rung": 3,
   "equity": 1.0,
   "peak": 1.0,
   "positions": {},
   "trades": 0,
   "days_in_market": 0,
   "sum_ret": 0.0,
   "sum_sq": 0.0,
   "paper_failures": 0,
   "retired": false,
   "history": [
    [
     "2026-07-13",
     0.0,
     1.0
    ],
    [
     "2026-07-10",
     0.0,
     1.0
    ],
    [
     "2026-07-10",
     0.0,
     1.0
    ]
   ]
  },
  "event_cement_t50": {
   "rung": 0,
   "days_on_rung": 3,
   "equity": 1.0,
   "peak": 1.0,
   "positions": {},
   "trades": 0,
   "days_in_market": 0,
   "sum_ret": 0.0,
   "sum_sq": 0.0,
   "paper_failures": 0,
   "retired": false,
   "history": [
    [
     "2026-07-13",
     0.0,
     1.0
    ],
    [
     "2026-07-10",
     0.0,
     1.0
    ],
    [
     "2026-07-10",
     0.0,
     1.0
    ]
   ]
  },
  "event_infra_t30": {
   "rung": 0,
   "days_on_rung": 3,
   "equity": 1.0,
   "peak": 1.0,
   "positions": {},
   "trades": 0,
   "days_in_market": 0,
   "sum_ret": 0.0,
   "sum_sq": 0.0,
   "paper_failures": 0,
   "retired": false,
   "history": [
    [
     "2026-07-13",
     0.0,
     1.0
    ],
    [
     "2026-07-10",
     0.0,
     1.0
    ],
    [
     "2026-07-10",
     0.0,
     1.0
    ]
   ]
  },
  "event_infra_t40": {
   "rung": 0,
   "days_on_rung": 3,
   "equity": 1.0,
   "peak": 1.0,
   "positions": {},
   "trades": 0,
   "days_in_market": 0,
   "sum_ret": 0.0,
   "sum_sq": 0.0,
   "paper_failures": 0,
   "retired": false,
   "history": [
    [
     "2026-07-13",
     0.0,
     1.0
    ],
    [
     "2026-07-10",
     0.0,
     1.0
    ],
    [
     "2026-07-10",
     0.0,
     1.0
    ]
   ]
  },
  "event_infra_t50": {
   "rung": 0,
   "days_on_rung": 3,
   "equity": 1.0,
   "peak": 1.0,
   "positions": {},
   "trades": 0,
   "days_in_market": 0,
   "sum_ret": 0.0,
   "sum_sq": 0.0,
   "paper_failures": 0,
   "retired": false,
   "history": [
    [
     "2026-07-13",
     0.0,
     1.0
    ],
    [
     "2026-07-10",
     0.0,
     1.0
    ],
    [
     "2026-07-10",
     0.0,
     1.0
    ]
   ]
  },
  "event_steel_t30": {
   "rung": 0,
   "days_on_rung": 3,
   "equity": 1.0,
   "peak": 1.0,
   "positions": {},
   "trades": 0,
   "days_in_market": 0,
   "sum_ret": 0.0,
   "sum_sq": 0.0,
   "paper_failures": 0,
   "retired": false,
   "history": [
    [
     "2026-07-13",
     0.0,
     1.0
    ],
    [
     "2026-07-10",
     0.0,
     1.0
    ],
    [
     "2026-07-10",
     0.0,
     1.0
    ]
   ]
  },
  "event_steel_t40": {
   "rung": 0,
   "days_on_rung": 3,
   "equity": 1.0,
   "peak": 1.0,
   "positions": {},
   "trades": 0,
   "days_in_market": 0,
   "sum_ret": 0.0,
   "sum_sq": 0.0,
   "paper_failures": 0,
   "retired": false,
   "history": [
    [
     "2026-07-13",
     0.0,
     1.0
    ],
    [
     "2026-07-10",
     0.0,
     1.0
    ],
    [
     "2026-07-10",
     0.0,
     1.0
    ]
   ]
  },
  "event_steel_t50": {
   "rung": 0,
   "days_on_rung": 3,
   "equity": 1.0,
   "peak": 1.0,
   "positions": {},
   "trades": 0,
   "days_in_market": 0,
   "sum_ret": 0.0,
   "sum_sq": 0.0,
   "paper_failures": 0,
   "retired": false,
   "history": [
    [
     "2026-07-13",
     0.0,
     1.0
    ],
    [
     "2026-07-10",
     0.0,
     1.0
    ],
    [
     "2026-07-10",
     0.0,
     1.0
    ]
   ]
  },
  "mom_cement_lb40": {
   "rung": 0,
   "days_on_rung": 3,
   "equity": 1.0321809709412,
   "peak": 1.0321809709412,
   "positions": {
    "SHREECEM.NS": 0.5,
    "RAMCOCEM.NS": 0.5
   },
   "trades": 1,
   "days_in_market": 2,
   "sum_ret": 0.033859236085427735,
   "sum_sq": 0.0005732239341443659,
   "paper_failures": 0,
   "retired": false,
   "history": [
    [
     "2026-07-13",
     -0.0019,
     0.9981
    ],
    [
     "2026-07-10",
     0.01693,
     1.015
    ],
    [
     "2026-07-10",
     0.01693,
     1.03218
    ]
   ]
  },
  "mom_cement_lb60": {
   "rung": 0,
   "days_on_rung": 3,
   "equity": 1.024793243961522,
   "peak": 1.024793243961522,
   "positions": {
    "SHREECEM.NS": 0.5,
    "ULTRACEMCO.NS": 0.5
   },
   "trades": 2,
   "days_in_market": 2,
   "sum_ret": 0.02656842297103469,
   "sum_sq": 0.0003546116990434548,
   "paper_failures": 0,
   "retired": false,
   "history": [
    [
     "2026-07-13",
     -0.0019,
     0.9981
    ],
    [
     "2026-07-10",
     0.01237,
     1.01045
    ],
    [
     "2026-07-10",
     0.014198,
     1.02479
    ]
   ]
  },
  "mom_cement_lb90": {
   "rung": 0,
   "days_on_rung": 3,
   "equity": 1.0149607243407381,
   "peak": 1.0149607243407381,
   "positions": {
    "SHREECEM.NS": 0.5,
    "JKCEMENT.NS": 0.5
   },
   "trades": 1,
   "days_in_market": 2,
   "sum_ret": 0.0168220751470054,
   "sum_sq": 0.00014149110612574837,
   "paper_failures": 0,
   "retired": false,
   "history": [
    [
     "2026-07-13",
     -0.0019,
     0.9981
    ],
    [
     "2026-07-10",
     0.008411,
     1.0065
    ],
    [
     "2026-07-10",
     0.008411,
     1.01496
    ]
   ]
  },
  "mom_infra_lb40": {
   "rung": 0,
   "days_on_rung": 3,
   "equity": 1.009205538901131,
   "peak": 1.009205538901131,
   "positions": {
    "PNCINFRA.NS": 1.0
   },
   "trades": 1,
   "days_in_market": 2,
   "sum_ret": 0.011095899844019375,
   "sum_sq": 6.155949667425459e-05,
   "paper_failures": 0,
   "retired": false,
   "history": [
    [
     "2026-07-13",
     -0.0019,
     0.9981
    ],
    [
     "2026-07-10",
     0.005548,
     1.00364
    ],
    [
     "2026-07-10",
     0.005548,
     1.00921
    ]
   ]
  },
  "mom_infra_lb60": {
   "rung": 0,
   "days_on_rung": 3,
   "equity": 1.009205538901131,
   "peak": 1.009205538901131,
   "positions": {
    "PNCINFRA.NS": 1.0
   },
   "trades": 1,
   "days_in_market": 2,
   "sum_ret": 0.011095899844019375,
   "sum_sq": 6.155949667425459e-05,
   "paper_failures": 0,
   "retired": false,
   "history": [
    [
     "2026-07-13",
     -0.0019,
     0.9981
    ],
    [
     "2026-07-10",
     0.005548,
     1.00364
    ],
    [
     "2026-07-10",
     0.005548,
     1.00921
    ]
   ]
  },
  "mom_infra_lb90": {
   "rung": 0,
   "days_on_rung": 3,
   "equity": 1.009205538901131,
   "peak": 1.009205538901131,
   "positions": {
    "PNCINFRA.NS": 1.0
   },
   "trades": 1,
   "days_in_market": 2,
   "sum_ret": 0.011095899844019375,
   "sum_sq": 6.155949667425459e-05,
   "paper_failures": 0,
   "retired": false,
   "history": [
    [
     "2026-07-13",
     -0.0019,
     0.9981
    ],
    [
     "2026-07-10",
     0.005548,
     1.00364
    ],
    [
     "2026-07-10",
     0.005548,
     1.00921
    ]
   ]
  },
  "mom_pipes_tiles_lb40": {
   "rung": 0,
   "days_on_rung": 3,
   "equity": 1.0030349739368998,
   "peak": 1.0030349739368998,
   "positions": {
    "KAJARIACER.NS": 1.0
   },
   "trades": 1,
   "days_in_market": 2,
   "sum_ret": 0.004938271604938205,
   "sum_sq": 1.2193263222069477e-05,
   "paper_failures": 0,
   "retired": false,
   "history": [
    [
     "2026-07-13",
     -0.0019,
     0.9981
    ],
    [
     "2026-07-10",
     0.002469,
     1.00056
    ],
    [
     "2026-07-10",
     0.002469,
     1.00303
    ]
   ]
  },
  "mom_pipes_tiles_lb60": {
   "rung": 0,
   "days_on_rung": 3,
   "equity": 1.0052522522978873,
   "peak": 1.0052522522978873,
   "positions": {
    "CERA.NS": 1.0
   },
   "trades": 1,
   "days_in_market": 2,
   "sum_ret": 0.007153075822603938,
   "sum_sq": 2.5583246861960502e-05,
   "paper_failures": 0,
   "retired": false,
   "history": [
    [
     "2026-07-13",
     -0.0019,
     0.9981
    ],
    [
     "2026-07-10",
     0.003577,
     1.00167
    ],
    [
     "2026-07-10",
     0.003577,
     1.00525
    ]
   ]
  },
  "mom_pipes_tiles_lb90": {
   "rung": 0,
   "days_on_rung": 3,
   "equity": 1.0003366560912414,
   "peak": 1.0003366560912414,
   "positions": {
    "CERA.NS": 1.0
   },
   "trades": 2,
   "days_in_market": 2,
   "sum_ret": 0.0022456737137710714,
   "sum_sq": 1.456282294324981e-05,
   "paper_failures": 0,
   "retired": false,
   "history": [
    [
     "2026-07-13",
     -0.0019,
     0.9981
    ],
    [
     "2026-07-10",
     -0.001331,
     0.99677
    ],
    [
     "2026-07-10",
     0.003577,
     1.00034
    ]
   ]
  },
  "input_cost_lag": {
   "rung": 0,
   "days_on_rung": 3,
   "equity": 1.0,
   "peak": 1.0,
   "positions": {},
   "trades": 0,
   "days_in_market": 0,
   "sum_ret": 0.0,
   "sum_sq": 0.0,
   "paper_failures": 0,
   "retired": false,
   "history": [
    [
     "2026-07-13",
     0.0,
     1.0
    ],
    [
     "2026-07-10",
     0.0,
     1.0
    ],
    [
     "2026-07-10",
     0.0,
     1.0
    ]
   ]
  },
  "monsoon_cement": {
   "rung": 0,
   "days_on_rung": 3,
   "equity": 1.0,
   "peak": 1.0,
   "positions": {},
   "trades": 0,
   "days_in_market": 0,
   "sum_ret": 0.0,
   "sum_sq": 0.0,
   "paper_failures": 0,
   "retired": false,
   "history": [
    [
     "2026-07-13",
     0.0,
     1.0
    ],
    [
     "2026-07-10",
     0.0,
     1.0
    ],
    [
     "2026-07-10",
     0.0,
     1.0
    ]
   ]
  }
 }
}