{
 "registry": {
  "event_cement_t30": {
   "fn": "event_drift",
   "sector": "cement",
   "leader": "ULTRACEMCO.NS",
   "threshold": 0.03,
   "hold": 3
  },
  "event_cement_t40": {
   "fn": "event_drift",
   "sector": "cement",
   "leader": "ULTRACEMCO.NS",
   "threshold": 0.04,
   "hold": 3
  },
  "event_cement_t50": {
   "fn": "event_drift",
   "sector": "cement",
   "leader": "ULTRACEMCO.NS",
   "threshold": 0.05,
   "hold": 3
  },
  "event_infra_t30": {
   "fn": "event_drift",
   "sector": "infra",
   "leader": "LT.NS",
   "threshold": 0.03,
   "hold": 3
  },
  "event_infra_t40": {
   "fn": "event_drift",
   "sector": "infra",
   "leader": "LT.NS",
   "threshold": 0.04,
   "hold": 3
  },
  "event_infra_t50": {
   "fn": "event_drift",
   "sector": "infra",
   "leader": "LT.NS",
   "threshold": 0.05,
   "hold": 3
  },
  "event_steel_t30": {
   "fn": "event_drift",
   "sector": "steel",
   "leader": "TATASTEEL.NS",
   "threshold": 0.03,
   "hold": 3
  },
  "event_steel_t40": {
   "fn": "event_drift",
   "sector": "steel",
   "leader": "TATASTEEL.NS",
   "threshold": 0.04,
   "hold": 3
  },
  "event_steel_t50": {
   "fn": "event_drift",
   "sector": "steel",
   "leader": "TATASTEEL.NS",
   "threshold": 0.05,
   "hold": 3
  },
  "mom_cement_lb40": {
   "fn": "momentum",
   "sector": "cement",
   "lookback": 40,
   "top_frac": 0.34
  },
  "mom_cement_lb60": {
   "fn": "momentum",
   "sector": "cement",
   "lookback": 60,
   "top_frac": 0.34
  },
  "mom_cement_lb90": {
   "fn": "momentum",
   "sector": "cement",
   "lookback": 90,
   "top_frac": 0.34
  },
  "mom_infra_lb40": {
   "fn": "momentum",
   "sector": "infra",
   "lookback": 40,
   "top_frac": 0.34
  },
  "mom_infra_lb60": {
   "fn": "momentum",
   "sector": "infra",
   "lookback": 60,
   "top_frac": 0.34
  },
  "mom_infra_lb90": {
   "fn": "momentum",
   "sector": "infra",
   "lookback": 90,
   "top_frac": 0.34
  },
  "mom_pipes_tiles_lb40": {
   "fn": "momentum",
   "sector": "pipes_tiles",
   "lookback": 40,
   "top_frac": 0.34
  },
  "mom_pipes_tiles_lb60": {
   "fn": "momentum",
   "sector": "pipes_tiles",
   "lookback": 60,
   "top_frac": 0.34
  },
  "mom_pipes_tiles_lb90": {
   "fn": "momentum",
   "sector": "pipes_tiles",
   "lookback": 90,
   "top_frac": 0.34
  },
  "input_cost_lag": {
   "fn": "input_cost",
   "sector": "cement",
   "proxy": "TATASTEEL.NS",
   "lb": 20,
   "drop": -0.05
  },
  "monsoon_cement": {
   "fn": "monsoon",
   "csv": "imd_rainfall_departure.csv",
   "lag": 10,
   "sector": "cement",
   "thresh": 10.0
  }
 },
 "contestants": {
  "event_cement_t30": {
   "rung": 0,
   "days_on_rung": 12,
   "equity": 1.0,
   "peak": 1.0,
   "positions": {},
   "trades": 0,
   "days_in_market": 0,
   "sum_ret": 0.0,
   "sum_sq": 0.0,
   "paper_failures": 0,
   "retired": false,
   "history": [
    [
     "2026-07-13",
     0.0,
     1.0
    ],
    [
     "2026-07-10",
     0.0,
     1.0
    ],
    [
     "2026-07-10",
     0.0,
     1.0
    ],
    [
     "2026-07-14",
     0.0,
     1.0
    ],
    [
     "2026-07-14",
     0.0,
     1.0
    ],
    [
     "2026-07-15",
     0.0,
     1.0
    ],
    [
     "2026-07-16",
     0.0,
     1.0
    ],
    [
     "2026-07-17",
     0.0,
     1.0
    ],
    [
     "2026-07-17",
     0.0,
     1.0
    ],
    [
     "2026-07-21",
     0.0,
     1.0
    ],
    [
     "2026-07-22",
     0.0,
     1.0
    ],
    [
     "2026-07-23",
     0.0,
     1.0
    ]
   ]
  },
  "event_cement_t40": {
   "rung": 0,
   "days_on_rung": 12,
   "equity": 1.0,
   "peak": 1.0,
   "positions": {},
   "trades": 0,
   "days_in_market": 0,
   "sum_ret": 0.0,
   "sum_sq": 0.0,
   "paper_failures": 0,
   "retired": false,
   "history": [
    [
     "2026-07-13",
     0.0,
     1.0
    ],
    [
     "2026-07-10",
     0.0,
     1.0
    ],
    [
     "2026-07-10",
     0.0,
     1.0
    ],
    [
     "2026-07-14",
     0.0,
     1.0
    ],
    [
     "2026-07-14",
     0.0,
     1.0
    ],
    [
     "2026-07-15",
     0.0,
     1.0
    ],
    [
     "2026-07-16",
     0.0,
     1.0
    ],
    [
     "2026-07-17",
     0.0,
     1.0
    ],
    [
     "2026-07-17",
     0.0,
     1.0
    ],
    [
     "2026-07-21",
     0.0,
     1.0
    ],
    [
     "2026-07-22",
     0.0,
     1.0
    ],
    [
     "2026-07-23",
     0.0,
     1.0
    ]
   ]
  },
  "event_cement_t50": {
   "rung": 0,
   "days_on_rung": 12,
   "equity": 1.0,
   "peak": 1.0,
   "positions": {},
   "trades": 0,
   "days_in_market": 0,
   "sum_ret": 0.0,
   "sum_sq": 0.0,
   "paper_failures": 0,
   "retired": false,
   "history": [
    [
     "2026-07-13",
     0.0,
     1.0
    ],
    [
     "2026-07-10",
     0.0,
     1.0
    ],
    [
     "2026-07-10",
     0.0,
     1.0
    ],
    [
     "2026-07-14",
     0.0,
     1.0
    ],
    [
     "2026-07-14",
     0.0,
     1.0
    ],
    [
     "2026-07-15",
     0.0,
     1.0
    ],
    [
     "2026-07-16",
     0.0,
     1.0
    ],
    [
     "2026-07-17",
     0.0,
     1.0
    ],
    [
     "2026-07-17",
     0.0,
     1.0
    ],
    [
     "2026-07-21",
     0.0,
     1.0
    ],
    [
     "2026-07-22",
     0.0,
     1.0
    ],
    [
     "2026-07-23",
     0.0,
     1.0
    ]
   ]
  },
  "event_infra_t30": {
   "rung": 0,
   "days_on_rung": 12,
   "equity": 1.0,
   "peak": 1.0,
   "positions": {},
   "trades": 0,
   "days_in_market": 0,
   "sum_ret": 0.0,
   "sum_sq": 0.0,
   "paper_failures": 0,
   "retired": false,
   "history": [
    [
     "2026-07-13",
     0.0,
     1.0
    ],
    [
     "2026-07-10",
     0.0,
     1.0
    ],
    [
     "2026-07-10",
     0.0,
     1.0
    ],
    [
     "2026-07-14",
     0.0,
     1.0
    ],
    [
     "2026-07-14",
     0.0,
     1.0
    ],
    [
     "2026-07-15",
     0.0,
     1.0
    ],
    [
     "2026-07-16",
     0.0,
     1.0
    ],
    [
     "2026-07-17",
     0.0,
     1.0
    ],
    [
     "2026-07-17",
     0.0,
     1.0
    ],
    [
     "2026-07-21",
     0.0,
     1.0
    ],
    [
     "2026-07-22",
     0.0,
     1.0
    ],
    [
     "2026-07-23",
     0.0,
     1.0
    ]
   ]
  },
  "event_infra_t40": {
   "rung": 0,
   "days_on_rung": 12,
   "equity": 1.0,
   "peak": 1.0,
   "positions": {},
   "trades": 0,
   "days_in_market": 0,
   "sum_ret": 0.0,
   "sum_sq": 0.0,
   "paper_failures": 0,
   "retired": false,
   "history": [
    [
     "2026-07-13",
     0.0,
     1.0
    ],
    [
     "2026-07-10",
     0.0,
     1.0
    ],
    [
     "2026-07-10",
     0.0,
     1.0
    ],
    [
     "2026-07-14",
     0.0,
     1.0
    ],
    [
     "2026-07-14",
     0.0,
     1.0
    ],
    [
     "2026-07-15",
     0.0,
     1.0
    ],
    [
     "2026-07-16",
     0.0,
     1.0
    ],
    [
     "2026-07-17",
     0.0,
     1.0
    ],
    [
     "2026-07-17",
     0.0,
     1.0
    ],
    [
     "2026-07-21",
     0.0,
     1.0
    ],
    [
     "2026-07-22",
     0.0,
     1.0
    ],
    [
     "2026-07-23",
     0.0,
     1.0
    ]
   ]
  },
  "event_infra_t50": {
   "rung": 0,
   "days_on_rung": 12,
   "equity": 1.0,
   "peak": 1.0,
   "positions": {},
   "trades": 0,
   "days_in_market": 0,
   "sum_ret": 0.0,
   "sum_sq": 0.0,
   "paper_failures": 0,
   "retired": false,
   "history": [
    [
     "2026-07-13",
     0.0,
     1.0
    ],
    [
     "2026-07-10",
     0.0,
     1.0
    ],
    [
     "2026-07-10",
     0.0,
     1.0
    ],
    [
     "2026-07-14",
     0.0,
     1.0
    ],
    [
     "2026-07-14",
     0.0,
     1.0
    ],
    [
     "2026-07-15",
     0.0,
     1.0
    ],
    [
     "2026-07-16",
     0.0,
     1.0
    ],
    [
     "2026-07-17",
     0.0,
     1.0
    ],
    [
     "2026-07-17",
     0.0,
     1.0
    ],
    [
     "2026-07-21",
     0.0,
     1.0
    ],
    [
     "2026-07-22",
     0.0,
     1.0
    ],
    [
     "2026-07-23",
     0.0,
     1.0
    ]
   ]
  },
  "event_steel_t30": {
   "rung": 0,
   "days_on_rung": 12,
   "equity": 1.0,
   "peak": 1.0,
   "positions": {},
   "trades": 0,
   "days_in_market": 0,
   "sum_ret": 0.0,
   "sum_sq": 0.0,
   "paper_failures": 0,
   "retired": false,
   "history": [
    [
     "2026-07-13",
     0.0,
     1.0
    ],
    [
     "2026-07-10",
     0.0,
     1.0
    ],
    [
     "2026-07-10",
     0.0,
     1.0
    ],
    [
     "2026-07-14",
     0.0,
     1.0
    ],
    [
     "2026-07-14",
     0.0,
     1.0
    ],
    [
     "2026-07-15",
     0.0,
     1.0
    ],
    [
     "2026-07-16",
     0.0,
     1.0
    ],
    [
     "2026-07-17",
     0.0,
     1.0
    ],
    [
     "2026-07-17",
     0.0,
     1.0
    ],
    [
     "2026-07-21",
     0.0,
     1.0
    ],
    [
     "2026-07-22",
     0.0,
     1.0
    ],
    [
     "2026-07-23",
     0.0,
     1.0
    ]
   ]
  },
  "event_steel_t40": {
   "rung": 0,
   "days_on_rung": 12,
   "equity": 1.0,
   "peak": 1.0,
   "positions": {},
   "trades": 0,
   "days_in_market": 0,
   "sum_ret": 0.0,
   "sum_sq": 0.0,
   "paper_failures": 0,
   "retired": false,
   "history": [
    [
     "2026-07-13",
     0.0,
     1.0
    ],
    [
     "2026-07-10",
     0.0,
     1.0
    ],
    [
     "2026-07-10",
     0.0,
     1.0
    ],
    [
     "2026-07-14",
     0.0,
     1.0
    ],
    [
     "2026-07-14",
     0.0,
     1.0
    ],
    [
     "2026-07-15",
     0.0,
     1.0
    ],
    [
     "2026-07-16",
     0.0,
     1.0
    ],
    [
     "2026-07-17",
     0.0,
     1.0
    ],
    [
     "2026-07-17",
     0.0,
     1.0
    ],
    [
     "2026-07-21",
     0.0,
     1.0
    ],
    [
     "2026-07-22",
     0.0,
     1.0
    ],
    [
     "2026-07-23",
     0.0,
     1.0
    ]
   ]
  },
  "event_steel_t50": {
   "rung": 0,
   "days_on_rung": 12,
   "equity": 1.0,
   "peak": 1.0,
   "positions": {},
   "trades": 0,
   "days_in_market": 0,
   "sum_ret": 0.0,
   "sum_sq": 0.0,
   "paper_failures": 0,
   "retired": false,
   "history": [
    [
     "2026-07-13",
     0.0,
     1.0
    ],
    [
     "2026-07-10",
     0.0,
     1.0
    ],
    [
     "2026-07-10",
     0.0,
     1.0
    ],
    [
     "2026-07-14",
     0.0,
     1.0
    ],
    [
     "2026-07-14",
     0.0,
     1.0
    ],
    [
     "2026-07-15",
     0.0,
     1.0
    ],
    [
     "2026-07-16",
     0.0,
     1.0
    ],
    [
     "2026-07-17",
     0.0,
     1.0
    ],
    [
     "2026-07-17",
     0.0,
     1.0
    ],
    [
     "2026-07-21",
     0.0,
     1.0
    ],
    [
     "2026-07-22",
     0.0,
     1.0
    ],
    [
     "2026-07-23",
     0.0,
     1.0
    ]
   ]
  },
  "mom_cement_lb40": {
   "rung": 0,
   "days_on_rung": 12,
   "equity": 0.9995014322137215,
   "peak": 1.0322196769655612,
   "positions": {
    "JKCEMENT.NS": 0.5,
    "SHREECEM.NS": 0.5
   },
   "trades": 4,
   "days_in_market": 11,
   "sum_ret": 0.0020367455493904684,
   "sum_sq": 0.001271007298575864,
   "paper_failures": 0,
   "retired": false,
   "history": [
    [
     "2026-07-13",
     -0.0019,
     0.9981
    ],
    [
     "2026-07-10",
     0.01693,
     1.015
    ],
    [
     "2026-07-10",
     0.01693,
     1.03218
    ],
    [
     "2026-07-14",
     -0.007878,
     1.02405
    ],
    [
     "2026-07-14",
     -0.007846,
     1.01602
    ],
    [
     "2026-07-15",
     0.012984,
     1.02921
    ],
    [
     "2026-07-16",
     0.002927,
     1.03222
    ],
    [
     "2026-07-17",
     -0.011545,
     1.0203
    ],
    [
     "2026-07-17",
     -0.014964,
     1.00504
    ],
    [
     "2026-07-21",
     0.001135,
     1.00618
    ],
    [
     "2026-07-22",
     -0.000444,
     1.00573
    ],
    [
     "2026-07-23",
     -0.006192,
     0.9995
    ]
   ]
  },
  "mom_cement_lb60": {
   "rung": 0,
   "days_on_rung": 12,
   "equity": 1.0103801908798666,
   "peak": 1.0272941956403072,
   "positions": {
    "SHREECEM.NS": 0.5,
    "JKCEMENT.NS": 0.5
   },
   "trades": 5,
   "days_in_market": 11,
   "sum_ret": 0.012889364346560128,
   "sum_sq": 0.0013295581051300334,
   "paper_failures": 0,
   "retired": false,
   "history": [
    [
     "2026-07-13",
     -0.0019,
     0.9981
    ],
    [
     "2026-07-10",
     0.01237,
     1.01045
    ],
    [
     "2026-07-10",
     0.014198,
     1.02479
    ],
    [
     "2026-07-14",
     -0.008601,
     1.01598
    ],
    [
     "2026-07-14",
     -0.008778,
     1.00706
    ],
    [
     "2026-07-15",
     0.020092,
     1.02729
    ],
    [
     "2026-07-16",
     -0.004086,
     1.0231
    ],
    [
     "2026-07-17",
     -0.009574,
     1.0133
    ],
    [
     "2026-07-17",
     -0.009574,
     1.0036
    ],
    [
     "2026-07-21",
     0.013479,
     1.01713
    ],
    [
     "2026-07-22",
     -0.000444,
     1.01668
    ],
    [
     "2026-07-23",
     -0.006192,
     1.01038
    ]
   ]
  },
  "mom_cement_lb90": {
   "rung": 0,
   "days_on_rung": 12,
   "equity": 1.0254701836355757,
   "peak": 1.0323181563028034,
   "positions": {
    "SHREECEM.NS": 0.5,
    "JKCEMENT.NS": 0.5
   },
   "trades": 1,
   "days_in_market": 11,
   "sum_ret": 0.027795250048983144,
   "sum_sq": 0.0014993170780133974,
   "paper_failures": 0,
   "retired": false,
   "history": [
    [
     "2026-07-13",
     -0.0019,
     0.9981
    ],
    [
     "2026-07-10",
     0.008411,
     1.0065
    ],
    [
     "2026-07-10",
     0.008411,
     1.01496
    ],
    [
     "2026-07-14",
     -0.003494,
     1.01141
    ],
    [
     "2026-07-14",
     -0.003442,
     1.00793
    ],
    [
     "2026-07-15",
     0.01895,
     1.02703
    ],
    [
     "2026-07-16",
     0.001761,
     1.02884
    ],
    [
     "2026-07-17",
     -0.011159,
     1.01736
    ],
    [
     "2026-07-17",
     -0.011159,
     1.00601
    ],
    [
     "2026-07-21",
     0.026153,
     1.03232
    ],
    [
     "2026-07-22",
     -0.000444,
     1.03186
    ],
    [
     "2026-07-23",
     -0.006192,
     1.02547
    ]
   ]
  },
  "mom_infra_lb40": {
   "rung": 0,
   "days_on_rung": 12,
   "equity": 0.9376953445018932,
   "peak": 1.009205538901131,
   "positions": {
    "PNCINFRA.NS": 1.0
   },
   "trades": 1,
   "days_in_market": 11,
   "sum_ret": -0.06138936098643222,
   "sum_sq": 0.0020408399798357625,
   "paper_failures": 0,
   "retired": false,
   "history": [
    [
     "2026-07-13",
     -0.0019,
     0.9981
    ],
    [
     "2026-07-10",
     0.005548,
     1.00364
    ],
    [
     "2026-07-10",
     0.005548,
     1.00921
    ],
    [
     "2026-07-14",
     -0.016447,
     0.99261
    ],
    [
     "2026-07-14",
     -0.01184,
     0.98085
    ],
    [
     "2026-07-15",
     0.001513,
     0.98234
    ],
    [
     "2026-07-16",
     -0.003512,
     0.97889
    ],
    [
     "2026-07-17",
     0.00504,
     0.98382
    ],
    [
     "2026-07-17",
     0.00504,
     0.98878
    ],
    [
     "2026-07-21",
     -0.015115,
     0.97384
    ],
    [
     "2026-07-22",
     -0.035672,
     0.9391
    ],
    [
     "2026-07-23",
     -0.001493,
     0.9377
    ]
   ]
  },
  "mom_infra_lb60": {
   "rung": 0,
   "days_on_rung": 12,
   "equity": 0.9376953445018932,
   "peak": 1.009205538901131,
   "positions": {
    "PNCINFRA.NS": 1.0
   },
   "trades": 1,
   "days_in_market": 11,
   "sum_ret": -0.06138936098643222,
   "sum_sq": 0.0020408399798357625,
   "paper_failures": 0,
   "retired": false,
   "history": [
    [
     "2026-07-13",
     -0.0019,
     0.9981
    ],
    [
     "2026-07-10",
     0.005548,
     1.00364
    ],
    [
     "2026-07-10",
     0.005548,
     1.00921
    ],
    [
     "2026-07-14",
     -0.016447,
     0.99261
    ],
    [
     "2026-07-14",
     -0.01184,
     0.98085
    ],
    [
     "2026-07-15",
     0.001513,
     0.98234
    ],
    [
     "2026-07-16",
     -0.003512,
     0.97889
    ],
    [
     "2026-07-17",
     0.00504,
     0.98382
    ],
    [
     "2026-07-17",
     0.00504,
     0.98878
    ],
    [
     "2026-07-21",
     -0.015115,
     0.97384
    ],
    [
     "2026-07-22",
     -0.035672,
     0.9391
    ],
    [
     "2026-07-23",
     -0.001493,
     0.9377
    ]
   ]
  },
  "mom_infra_lb90": {
   "rung": 0,
   "days_on_rung": 12,
   "equity": 0.9376953445018932,
   "peak": 1.009205538901131,
   "positions": {
    "PNCINFRA.NS": 1.0
   },
   "trades": 1,
   "days_in_market": 11,
   "sum_ret": -0.06138936098643222,
   "sum_sq": 0.0020408399798357625,
   "paper_failures": 0,
   "retired": false,
   "history": [
    [
     "2026-07-13",
     -0.0019,
     0.9981
    ],
    [
     "2026-07-10",
     0.005548,
     1.00364
    ],
    [
     "2026-07-10",
     0.005548,
     1.00921
    ],
    [
     "2026-07-14",
     -0.016447,
     0.99261
    ],
    [
     "2026-07-14",
     -0.01184,
     0.98085
    ],
    [
     "2026-07-15",
     0.001513,
     0.98234
    ],
    [
     "2026-07-16",
     -0.003512,
     0.97889
    ],
    [
     "2026-07-17",
     0.00504,
     0.98382
    ],
    [
     "2026-07-17",
     0.00504,
     0.98878
    ],
    [
     "2026-07-21",
     -0.015115,
     0.97384
    ],
    [
     "2026-07-22",
     -0.035672,
     0.9391
    ],
    [
     "2026-07-23",
     -0.001493,
     0.9377
    ]
   ]
  },
  "mom_pipes_tiles_lb40": {
   "rung": 0,
   "days_on_rung": 12,
   "equity": 0.9756077519347223,
   "peak": 1.0056231531752164,
   "positions": {
    "KAJARIACER.NS": 1.0
   },
   "trades": 1,
   "days_in_market": 11,
   "sum_ret": -0.02258295212412731,
   "sum_sq": 0.00041620785791707834,
   "paper_failures": 0,
   "retired": false,
   "history": [
    [
     "2026-07-13",
     -0.0019,
     0.9981
    ],
    [
     "2026-07-10",
     0.002469,
     1.00056
    ],
    [
     "2026-07-10",
     0.002469,
     1.00303
    ],
    [
     "2026-07-14",
     -0.001779,
     1.00125
    ],
    [
     "2026-07-14",
     -0.001537,
     0.99971
    ],
    [
     "2026-07-15",
     0.002025,
     1.00174
    ],
    [
     "2026-07-16",
     0.00388,
     1.00562
    ],
    [
     "2026-07-17",
     -0.001852,
     1.00376
    ],
    [
     "2026-07-17",
     -0.001852,
     1.0019
    ],
    [
     "2026-07-21",
     -0.010385,
     0.9915
    ],
    [
     "2026-07-22",
     0.000244,
     0.99174
    ],
    [
     "2026-07-23",
     -0.016265,
     0.97561
    ]
   ]
  },
  "mom_pipes_tiles_lb60": {
   "rung": 0,
   "days_on_rung": 12,
   "equity": 0.9498011420899526,
   "peak": 1.0052522522978873,
   "positions": {
    "CERA.NS": 1.0
   },
   "trades": 1,
   "days_in_market": 11,
   "sum_ret": -0.04910896869182968,
   "sum_sq": 0.000974729920215404,
   "paper_failures": 0,
   "retired": false,
   "history": [
    [
     "2026-07-13",
     -0.0019,
     0.9981
    ],
    [
     "2026-07-10",
     0.003577,
     1.00167
    ],
    [
     "2026-07-10",
     0.003577,
     1.00525
    ],
    [
     "2026-07-14",
     -0.002277,
     1.00296
    ],
    [
     "2026-07-14",
     -0.001871,
     1.00109
    ],
    [
     "2026-07-15",
     -0.004726,
     0.99636
    ],
    [
     "2026-07-16",
     0.001556,
     0.99791
    ],
    [
     "2026-07-17",
     -0.011363,
     0.98657
    ],
    [
     "2026-07-17",
     -0.011363,
     0.97536
    ],
    [
     "2026-07-21",
     0.007763,
     0.98293
    ],
    [
     "2026-07-22",
     -0.020141,
     0.96313
    ],
    [
     "2026-07-23",
     -0.01384,
     0.9498
    ]
   ]
  },
  "mom_pipes_tiles_lb90": {
   "rung": 0,
   "days_on_rung": 12,
   "equity": 0.9432157091511422,
   "peak": 1.0003366560912414,
   "positions": {
    "KAJARIACER.NS": 1.0
   },
   "trades": 5,
   "days_in_market": 11,
   "sum_ret": -0.05600631027965498,
   "sum_sq": 0.0010932939727125895,
   "paper_failures": 0,
   "retired": false,
   "history": [
    [
     "2026-07-13",
     -0.0019,
     0.9981
    ],
    [
     "2026-07-10",
     -0.001331,
     0.99677
    ],
    [
     "2026-07-10",
     0.003577,
     1.00034
    ],
    [
     "2026-07-14",
     -0.006077,
     0.99426
    ],
    [
     "2026-07-14",
     -0.001537,
     0.99273
    ],
    [
     "2026-07-15",
     0.002025,
     0.99474
    ],
    [
     "2026-07-16",
     8e-05,
     0.99482
    ],
    [
     "2026-07-17",
     -0.011363,
     0.98352
    ],
    [
     "2026-07-17",
     -0.011363,
     0.97234
    ],
    [
     "2026-07-21",
     0.007763,
     0.97989
    ],
    [
     "2026-07-22",
     -0.020141,
     0.96015
    ],
    [
     "2026-07-23",
     -0.01764,
     0.94322
    ]
   ]
  },
  "input_cost_lag": {
   "rung": 0,
   "days_on_rung": 12,
   "equity": 1.0114828551081965,
   "peak": 1.0116613804011818,
   "positions": {},
   "trades": 2,
   "days_in_market": 6,
   "sum_ret": 0.01358180020154236,
   "sum_sq": 0.0005301702802371414,
   "paper_failures": 0,
   "retired": false,
   "history": [
    [
     "2026-07-13",
     0.0,
     1.0
    ],
    [
     "2026-07-10",
     0.0,
     1.0
    ],
    [
     "2026-07-10",
     0.0,
     1.0
    ],
    [
     "2026-07-14",
     -0.0019,
     0.9981
    ],
    [
     "2026-07-14",
     -0.005548,
     0.99256
    ],
    [
     "2026-07-15",
     0.019242,
     1.01166
    ],
    [
     "2026-07-16",
     -0.001111,
     1.01054
    ],
    [
     "2026-07-17",
     -0.004278,
     1.00621
    ],
    [
     "2026-07-17",
     -0.004278,
     1.00191
    ],
    [
     "2026-07-21",
     0.009555,
     1.01148
    ],
    [
     "2026-07-22",
     0.0,
     1.01148
    ],
    [
     "2026-07-23",
     0.0,
     1.01148
    ]
   ]
  },
  "monsoon_cement": {
   "rung": 0,
   "days_on_rung": 12,
   "equity": 1.0,
   "peak": 1.0,
   "positions": {},
   "trades": 0,
   "days_in_market": 0,
   "sum_ret": 0.0,
   "sum_sq": 0.0,
   "paper_failures": 0,
   "retired": false,
   "history": [
    [
     "2026-07-13",
     0.0,
     1.0
    ],
    [
     "2026-07-10",
     0.0,
     1.0
    ],
    [
     "2026-07-10",
     0.0,
     1.0
    ],
    [
     "2026-07-14",
     0.0,
     1.0
    ],
    [
     "2026-07-14",
     0.0,
     1.0
    ],
    [
     "2026-07-15",
     0.0,
     1.0
    ],
    [
     "2026-07-16",
     0.0,
     1.0
    ],
    [
     "2026-07-17",
     0.0,
     1.0
    ],
    [
     "2026-07-17",
     0.0,
     1.0
    ],
    [
     "2026-07-21",
     0.0,
     1.0
    ],
    [
     "2026-07-22",
     0.0,
     1.0
    ],
    [
     "2026-07-23",
     0.0,
     1.0
    ]
   ]
  }
 }
}